adranis_sigma/__init__.py
adranis_sigma/uq/__init__.py
adranis_sigma/uq/display_util.py
adranis_sigma/uq/helpers.py
adranis_sigma/uq/interface.py
adranis_sigma/uq/sessions.py
adranis_sigma/uq/test_comp_models.py
adranis_sigma-0.1.0.dist-info/LICENSE
adranis_sigma-0.1.0.dist-info/WHEEL
adranis_sigma-0.1.0.dist-info/METADATA
adranis_sigma-0.1.0.dist-info/RECORD
